smol_db/__init__.py
smol_db/core/database.py
smol_db/core/index.py
smol_db/core/table.py
smol_db/storage/engine.py
smol_db-0.1.0.dist-info/METADATA
smol_db-0.1.0.dist-info/WHEEL
smol_db-0.1.0.dist-info/licenses/LICENSE
smol_db-0.1.0.dist-info/RECORD
