Metadata-Version: 2.4
Name: smol-db
Version: 0.1.0
Summary: A database system built on top of smol-format for efficient storage and querying of structured data with exact rational number support
Author-email: Joshua Small <small.joshua@gmail.com>
License-Expression: MIT
License-File: LICENSE
Classifier: Development Status :: 3 - Alpha
Classifier: Intended Audience :: Science/Research
Classifier: License :: OSI Approved :: MIT License
Classifier: Programming Language :: Python :: 3
Classifier: Programming Language :: Python :: 3.8
Classifier: Programming Language :: Python :: 3.9
Classifier: Programming Language :: Python :: 3.10
Classifier: Programming Language :: Python :: 3.11
Classifier: Topic :: Database :: Database Engines/Servers
Classifier: Topic :: Scientific/Engineering :: Mathematics
Requires-Python: >=3.9
Requires-Dist: pydantic>=2.0.0
Requires-Dist: smol-format>=0.1.2
Requires-Dist: typing-extensions>=4.0.0
Requires-Dist: zstandard>=0.21.0
Provides-Extra: dev
Requires-Dist: black>=23.0.0; extra == 'dev'
Requires-Dist: flake8>=6.0.0; extra == 'dev'
Requires-Dist: isort>=5.0.0; extra == 'dev'
Requires-Dist: mypy>=1.0.0; extra == 'dev'
Requires-Dist: pytest-cov>=4.0.0; extra == 'dev'
Requires-Dist: pytest>=7.0.0; extra == 'dev'
